{"ast":null,"code":"require(\"jquery\");\n\nrequire(\"jquery-ui\");\n\nrequire(\"jquery/sortable\");","map":{"version":3,"sources":["/home/silver/lakeside_lab/rails_plugins/poshcentral_plugin/aristo_lms/app/javascript/aristo_lms/packs/application.js"],"names":["require"],"mappings":"AAAAA,OAAO,CAAC,QAAD,CAAP;;AACAA,OAAO,CAAC,WAAD,CAAP;;AACAA,OAAO,CAAC,iBAAD,CAAP","sourcesContent":["require(\"jquery\")\nrequire(\"jquery-ui\")\nrequire(\"jquery/sortable\")\n"]},"metadata":{},"sourceType":"module"}